Metadata-Version: 2.1
Name: JupyterNotebookReflection
Version: 0.0.11
Summary: A module to perform reflection coding in Jupyter notebooks.
Home-page: UNKNOWN
Author: Charles Varley
License: MIT
Keywords: jupyter,notebook,reflection,introspection
Platform: UNKNOWN
